{"7cs6wgrtx98i":{"entity":{"id":212,"template_code":"thoitrang05","code":"tyc9jrx","name":"Breadcrums","type":"html","action":"","view":"tyc9jrx.tpl","element_view":"","config":"{\"class\":\"\",\"cache\":\"0\",\"html_content\":\"<nav class=\\\"breadcrumbs-section my-3\\\">\\r\\n\\t<a href=\\\"\\\/\\\">\\r\\n\\t    {__d('template', 'trang_chu')}\\r\\n\\t<\\\/a>\\r\\n\\t{if !empty($breadcrumb)}\\r\\n\\t    {foreach from = $breadcrumb item = item name = breadcrumb_each}\\r\\n\\t        {if !$smarty.foreach.breadcrumb_each.last}\\r\\n\\t            {if !empty($item.url)}\\r\\n    \\t            <a href=\\\"{$this->Utilities->checkInternalUrl($item.url)}\\\">\\r\\n    \\t                {if !empty($item.name)}\\r\\n    \\t                    {$item.name|escape|truncate:50:\\\" ...\\\"}\\r\\n    \\t                {\\\/if}\\r\\n    \\t            <\\\/a>\\r\\n\\t            {\\\/if}\\r\\n\\t        {else}\\r\\n                <a href=\\\"{$this->Utilities->checkInternalUrl($item.url)}\\\">\\r\\n\\t                <span>\\r\\n                \\t    {if !empty($item.name)}\\r\\n    \\t                    {$item.name|escape|truncate:50:\\\" ...\\\"}\\r\\n    \\t                {\\\/if}\\r\\n            \\t    <\\\/span>\\r\\n        \\t    <\\\/a>\\r\\n\\t        {\\\/if}\\r\\n\\t    {\\\/foreach}\\r\\n\\t{\\\/if}\\r\\n<\\\/nav>\"}","data_extend":"","normal_data_extend":"","collection_data_extend":"","created":1662951833,"created_by":0,"updated":1742535029,"status":1,"search_unicode":"breadcrums | tyc9jrx","deleted":0},"before_entity":[]}}